LICENSE
MANIFEST.in
README.md
requirements.txt
setup.cfg
setup.py
ipyslickgrid/__init__.py
ipyslickgrid/_version.py
ipyslickgrid/grid.py
ipyslickgrid.egg-info/PKG-INFO
ipyslickgrid.egg-info/SOURCES.txt
ipyslickgrid.egg-info/dependency_links.txt
ipyslickgrid.egg-info/not-zip-safe
ipyslickgrid.egg-info/requires.txt
ipyslickgrid.egg-info/top_level.txt
ipyslickgrid/pd_json/__init__.py
ipyslickgrid/pd_json/json.py
ipyslickgrid/pd_json/normalize.py
ipyslickgrid/pd_json/table_schema.py
ipyslickgrid/tests/__init__.py
ipyslickgrid/tests/test_grid.py